youtube_tts_data_generator/__init__.py
youtube_tts_data_generator/audio.py
youtube_tts_data_generator/number_cleaner.py
youtube_tts_data_generator/text_cleaner.py
youtube_tts_data_generator/youtube_tts_data_generator.py
youtube_tts_data_generator-0.2.1.dist-info/LICENSE
youtube_tts_data_generator-0.2.1.dist-info/METADATA
youtube_tts_data_generator-0.2.1.dist-info/WHEEL
youtube_tts_data_generator-0.2.1.dist-info/top_level.txt
youtube_tts_data_generator-0.2.1.dist-info/RECORD
